langchain_fc_barcelona/__init__.py
langchain_fc_barcelona/chat_model_fc_barcelona.py
langchain_fc_barcelona-0.1.0.dist-info/METADATA
langchain_fc_barcelona-0.1.0.dist-info/WHEEL
langchain_fc_barcelona-0.1.0.dist-info/RECORD
