Metadata-Version: 2.1
Name: langchain-fc-barcelona
Version: 0.1.0
Summary: 
Author: isaac hershenson
Author-email: ihershenson@hmc.edu
Requires-Python: >=3.11,<4.0
Classifier: Programming Language :: Python :: 3
Classifier: Programming Language :: Python :: 3.11
Classifier: Programming Language :: Python :: 3.12
Requires-Dist: langchain-core (>=0.3.19,<0.4.0)
